sg_nric/__init__.py
sg_nric/validator.py
sg_nric_validator-0.0.1.dist-info/LICENSE
sg_nric_validator-0.0.1.dist-info/METADATA
sg_nric_validator-0.0.1.dist-info/WHEEL
sg_nric_validator-0.0.1.dist-info/top_level.txt
sg_nric_validator-0.0.1.dist-info/RECORD
