Metadata-Version: 2.1
Name: sg-nric-validator
Version: 0.0.1
Summary: Validation tools for Singapore NRIC
Home-page: https://github.com/kyorilys/SGNRICValidator
Author: kyorilys
Author-email: kyorilys_256@live.com
License: UNKNOWN
Project-URL: Bug Tracker, https://github.com/kyorilys/SGNRICValidator/issues
Platform: UNKNOWN
Classifier: Programming Language :: Python :: 3
Classifier: License :: OSI Approved :: MIT License
Classifier: Operating System :: OS Independent
Requires-Python: >=3.6
License-File: LICENSE
